eptlsoot/__init__.py
eptlsoot/cpfr.py
eptlsoot/eptlsoot.py
eptlsoot/psr.py
eptlsoot/apps/__init__.py
eptlsoot/apps/flame.py
eptlsoot/apps/pahgrowth.py
eptlsoot/apps/reactors.py
eptlsoot/apps/solutionarray.py
eptlsoot/apps/sootgas.py
eptlsoot/apps/sootmodels.py
eptlsoot/apps/sootwrappers.py
eptlsoot/apps/surfacereactions.py
eptlsoot/lib/_eptlsoot.cp37-win_amd64.pyd
eptlsoot-0.0.9.dist-info/METADATA
eptlsoot-0.0.9.dist-info/WHEEL
eptlsoot-0.0.9.dist-info/top_level.txt
eptlsoot-0.0.9.dist-info/RECORD
