Metadata-Version: 2.1
Name: eptlsoot
Version: 0.0.9
Summary: Soot model from EPTL group
Author-email: Mo Adib <moademic@gmail.com>
Project-URL: Homepage, https://carleton.ca/eptl/people/336/
Keywords: computational,soot
Classifier: Programming Language :: Python :: 3
Requires-Python: >=3.7
